microprobe/definitions/power/__init__.py
microprobe/definitions/power/doc/__init__.py
microprobe/definitions/power/doc/examples.rst
microprobe/definitions/power/doc/examples_power.rst
microprobe/definitions/power/env/__init__.py
microprobe/definitions/power/env/powerpc64_linux_gcc.py
microprobe/definitions/power/examples/__init__.py
microprobe/definitions/power/examples/genetic_eval.sh
microprobe/definitions/power/examples/isa_power_v206_info.py
microprobe/definitions/power/examples/power_v206_power7_ppc64_linux_gcc_custom.py
microprobe/definitions/power/examples/power_v206_power7_ppc64_linux_gcc_fu_stress.py
microprobe/definitions/power/examples/power_v206_power7_ppc64_linux_gcc_genetic.py
microprobe/definitions/power/examples/power_v206_power7_ppc64_linux_gcc_memory.py
microprobe/definitions/power/examples/power_v206_power7_ppc64_linux_gcc_profile.py
microprobe/definitions/power/examples/power_v206_power7_ppc64_linux_gcc_random.py
microprobe/definitions/power/isa/__init__.py
microprobe/definitions/power/isa/p-common/__init__.py
microprobe/definitions/power/isa/p-common/comparator.py
microprobe/definitions/power/isa/p-common/generator.py
microprobe/definitions/power/isa/p-common/getcontext.S
microprobe/definitions/power/isa/p-common/instruction.py
microprobe/definitions/power/isa/p-common/instruction.yaml
microprobe/definitions/power/isa/p-common/instruction_field.py
microprobe/definitions/power/isa/p-common/instruction_field.yaml
microprobe/definitions/power/isa/p-common/instruction_format.py
microprobe/definitions/power/isa/p-common/instruction_format.yaml
microprobe/definitions/power/isa/p-common/isa.py
microprobe/definitions/power/isa/p-common/isa.yaml
microprobe/definitions/power/isa/p-common/operand.py
microprobe/definitions/power/isa/p-common/operand.yaml
microprobe/definitions/power/isa/p-common/register.py
microprobe/definitions/power/isa/p-common/register.yaml
microprobe/definitions/power/isa/p-common/register_type.py
microprobe_target_power-0.5.20250911152917.dist-info/licenses/LICENSE
microprobe_target_power-0.5.20250911152917.dist-info/METADATA
microprobe_target_power-0.5.20250911152917.dist-info/WHEEL
microprobe_target_power-0.5.20250911152917.dist-info/entry_points.txt
microprobe_target_power-0.5.20250911152917.dist-info/top_level.txt
microprobe_target_power-0.5.20250911152917.dist-info/RECORD
