Metadata-Version: 2.4
Name: microprobe_target_power
Version: 0.5.20250911152917
Summary: Microprobe: Microbenchmark generation framework: Target definitions for POWER
Home-page: https://github.com/IBM/microprobe
Author: Ramon Bertran
Author-email: rbertra@us.ibm.com
Maintainer: Ramon Bertran
Maintainer-email: rbertra@us.ibm.com
License: Apache Version 2.0
Keywords: microprobe microbenchmarks code generation stresstests characterization computer architecture microarchitecture
Platform: none-any
Classifier: Development Status :: 4 - Beta
Classifier: Environment :: Console
Classifier: Intended Audience :: Science/Research
Classifier: License :: OSI Approved :: Apache Software License
Classifier: Natural Language :: English
Classifier: Operating System :: POSIX :: Linux
Classifier: Programming Language :: Python :: 3
Classifier: Programming Language :: Python :: 3.7
Classifier: Programming Language :: Python :: 3.8
Classifier: Programming Language :: Python :: 3.9
Classifier: Topic :: Scientific/Engineering
Classifier: Topic :: Scientific/Engineering :: Electronic Design Automation (EDA)
Classifier: Topic :: Software Development
Classifier: Topic :: Software Development :: Code Generators
Classifier: Topic :: Utilities
License-File: LICENSE
Requires-Dist: microprobe_core>=0.5
Dynamic: author
Dynamic: author-email
Dynamic: classifier
Dynamic: description
Dynamic: home-page
Dynamic: keywords
Dynamic: license
Dynamic: license-file
Dynamic: maintainer
Dynamic: maintainer-email
Dynamic: platform
Dynamic: requires-dist
Dynamic: summary
